polars_ols-0.3.5.dist-info/METADATA
polars_ols-0.3.5.dist-info/WHEEL
polars_ols-0.3.5.dist-info/licenses/LICENSE
polars_ols/least_squares.py
polars_ols/utils.py
polars_ols/__init__.py
polars_ols/_polars_ols.abi3.so
polars_ols-0.3.5.dist-info/RECORD
