Metadata-Version: 2.3
Name: polars-ols
Version: 0.3.5
Classifier: Programming Language :: Rust
Classifier: Programming Language :: Python :: Implementation :: CPython
Classifier: Programming Language :: Python :: Implementation :: PyPy
Requires-Dist: polars >=0.20.16
Requires-Dist: numpy ; extra == 'dev'
Requires-Dist: pytest >=7.4.1 ; extra == 'dev'
Requires-Dist: pre-commit ; extra == 'dev'
Requires-Dist: statsmodels ; extra == 'dev'
Provides-Extra: dev
License-File: LICENSE
Summary: Polars Least Squares Extension
Keywords: polars-extension,linear-regression
Author-email: Azmy Rajab <azmy.rajab@gmail.com>
Requires-Python: >=3.8
